odoo/addons/mail_notification_with_history/README.rst
odoo/addons/mail_notification_with_history/__init__.py
odoo/addons/mail_notification_with_history/__manifest__.py
odoo/addons/mail_notification_with_history/data/mail_data.xml
odoo/addons/mail_notification_with_history/i18n/mail_notification_with_history.pot
odoo/addons/mail_notification_with_history/models/__init__.py
odoo/addons/mail_notification_with_history/models/mail_message.py
odoo/addons/mail_notification_with_history/models/mail_thread.py
odoo/addons/mail_notification_with_history/readme/CONTRIBUTORS.rst
odoo/addons/mail_notification_with_history/readme/DESCRIPTION.rst
odoo/addons/mail_notification_with_history/readme/INSTALL.rst
odoo/addons/mail_notification_with_history/static/description/icon.png
odoo/addons/mail_notification_with_history/static/description/index.html
odoo/addons/mail_notification_with_history/tests/__init__.py
odoo/addons/mail_notification_with_history/tests/test_mail_notification_with_history.py
odoo14_addon_mail_notification_with_history-14.0.1.0.1.dist-info/METADATA
odoo14_addon_mail_notification_with_history-14.0.1.0.1.dist-info/WHEEL
odoo14_addon_mail_notification_with_history-14.0.1.0.1.dist-info/top_level.txt
odoo14_addon_mail_notification_with_history-14.0.1.0.1.dist-info/RECORD
