Metadata-Version: 2.1
Name: odoo14-addon-mail-notification-with-history
Version: 14.0.1.0.1
Summary: Add the previous chatter discussion into new email notifications.
Home-page: https://github.com/OCA/social
Author: Camptocamp SA, Odoo Community Association (OCA)
Author-email: support@odoo-community.org
License: AGPL-3
Platform: UNKNOWN
Classifier: Programming Language :: Python
Classifier: Framework :: Odoo
Classifier: Framework :: Odoo :: 14.0
Classifier: License :: OSI Approved :: GNU Affero General Public License v3
Classifier: Development Status :: 4 - Beta
Requires-Python: >=3.6
Requires-Dist: odoo (<14.1dev,>=14.0a)
